pg_migration/__init__.py
pg_migration/distribute_upgrader.py
pg_migration/gitlab.py
pg_migration/initializer.py
pg_migration/main.py
pg_migration/migration.py
pg_migration/pg.py
pg_migration/plpgsql_checker.py
pg_migration/release_generator.py
pg_migration/upgrader.py
pg_migration-1.5.0.dist-info/AUTHORS
pg_migration-1.5.0.dist-info/LICENSE
pg_migration-1.5.0.dist-info/METADATA
pg_migration-1.5.0.dist-info/WHEEL
pg_migration-1.5.0.dist-info/entry_points.txt
pg_migration-1.5.0.dist-info/top_level.txt
pg_migration-1.5.0.dist-info/RECORD
