Metadata-Version: 2.1
Name: pg-migration
Version: 1.5.0
Summary: postgres ci/cd automation
Home-page: https://github.com/comagic/pg_migration
Author: Andrey Chernyakov
Author-email: a.chernyakov@comagic.dev
License: BSD
Project-URL: Documentation, https://github.com/comagic/pg_migration/blob/master/README.md
Project-URL: Bug Tracker, https://github.com/comagic/pg_migration/issues
Keywords: postgresql,git,ci/cd
Classifier: Development Status :: 5 - Production/Stable
Classifier: Environment :: Console
Classifier: Operating System :: OS Independent
Classifier: Programming Language :: Python :: 3.6
Classifier: Programming Language :: Python :: 3.7
Classifier: Programming Language :: Python :: 3.8
Classifier: Programming Language :: Python :: 3.9
Classifier: Programming Language :: Python :: 3.10
Requires-Python: >=3.8
License-File: LICENSE
License-File: AUTHORS
Requires-Dist: asyncpg<0.31.0,>=0.27.0
Requires-Dist: GitPython==3.1.42
Requires-Dist: urllib3==1.26.6
Requires-Dist: python-gitlab==4.4.0
